<Properties StartupConfiguration="{65E644B1-3287-6674-EC08-F5D5C91D6FCA}|">
  <MonoDevelop.Ide.Workbench ActiveDocument="Assets/Scripts/PlayerController.cs">
    <Files>
      <File FileName="Assets/Scripts/PlayerController.cs" Line="71" Column="11" />
      <File FileName="Assets/Scripts/BulletBehaviour.cs" />
      <File FileName="Assets/Scripts/LargeAsteroidBehaviour.cs" />
      <File FileName="Assets/Scripts/AsteroidSpawner.cs" />
      <File FileName="Assets/Scripts/ScreenWrapping.cs" Line="20" Column="66" />
    </Files>
    <Pads>
      <Pad Id="ProjectPad">
        <State name="__root__">
          <Node name="AsteroidsGame" expanded="True">
            <Node name="Assets" expanded="True">
              <Node name="Scripts" expanded="True">
                <Node name="PlayerController.cs" selected="True" />
              </Node>
            </Node>
          </Node>
        </State>
      </Pad>
    </Pads>
  </MonoDevelop.Ide.Workbench>
  <MonoDevelop.Ide.DebuggingService.PinnedWatches />
  <MonoDevelop.Ide.Workspace ActiveConfiguration="Debug" />
  <MonoDevelop.Ide.ItemProperties.Assembly-CSharp PreferredExecutionTarget="fba131c9-fe88-4eb0-aa26-52f8a72bfbd0" />
  <MonoDevelop.Ide.DebuggingService.Breakpoints>
    <BreakpointStore />
  </MonoDevelop.Ide.DebuggingService.Breakpoints>
  <MultiItemStartupConfigurations />
</Properties>